[
  {
    "id": "nakiishi",
    "open_codes": [
      {
        "code": "夜間の泣き声表出",
        "category": "行動様式",
        "property": "音響的訴求",
        "dimension": "時間的周期性"
      },
      {
        "code": "供養要求による静寂",
        "category": "関係性",
        "property": "宗教的交換",
        "dimension": "相互扶助的"
      },
      {
        "code": "無念の物質化",
        "category": "存在論",
        "property": "感情の石化",
        "dimension": "永続的悲嘆"
      },
      {
        "code": "境界での慰霊媒介",
        "category": "存在論",
        "property": "生死の架橋",
        "dimension": "霊的調整"
      },
      {
        "code": "赤子模倣による共感喚起",
        "category": "言説",
        "property": "原初的訴求",
        "dimension": "普遍的母性"
      }
    ]
  },
  {
    "id": "youkai_market",
    "open_codes": [
      {
        "code": "異世界商業活動",
        "category": "行動様式",
        "property": "妖怪間取引",
        "dimension": "経済的媒介"
      },
      {
        "code": "隠密的人間支援",
        "category": "関係性",
        "property": "匿名の恩恵",
        "dimension": "一方向的援助"
      },
      {
        "code": "境界領域での仲介",
        "category": "存在論",
        "property": "異種族媒介",
        "dimension": "文化的翻訳"
      },
      {
        "code": "商業的語彙使用",
        "category": "言説",
        "property": "売買の呼びかけ",
        "dimension": "実用的コミュニケーション"
      },
      {
        "code": "適応的商品提供",
        "category": "行動様式",
        "property": "需要対応",
        "dimension": "柔軟性"
      }
    ]
  },
  {
    "id": "jiuwei_hu",
    "open_codes": [
      {
        "code": "美的変身による権力浸透",
        "category": "行動様式",
        "property": "政治的潜入",
        "dimension": "長期戦略的"
      },
      {
        "code": "徳性試験の執行",
        "category": "関係性",
        "property": "道徳的判定",
        "dimension": "善悪二元的"
      },
      {
        "code": "千年視座での人間観察",
        "category": "存在論",
        "property": "超時間的知恵",
        "dimension": "宇宙的洞察"
      },
      {
        "code": "知恵と美の二刃性表現",
        "category": "言説",
        "property": "哲学的警告",
        "dimension": "弁証法的"
      },
      {
        "code": "瞑想による霊力修行",
        "category": "行動様式",
        "property": "自己修練",
        "dimension": "継続的成長"
      },
      {
        "code": "社会変革の天的代理",
        "category": "存在論",
        "property": "宇宙的使命",
        "dimension": "超越的正義"
      }
    ]
  },
  {
    "id": "kyubi_no_kitsune",
    "open_codes": [
      {
        "code": "美的誘惑による権力掌握",
        "category": "行動様式",
        "property": "政治的操作",
        "dimension": "破壊的支配"
      },
      {
        "code": "幻術と火炎による戦闘",
        "category": "行動様式",
        "property": "超自然的攻撃",
        "dimension": "激烈な抵抗"
      },
      {
        "code": "千年恨の表出",
        "category": "言説",
        "property": "復讐的宣言",
        "dimension": "感情的激烈"
      },
      {
        "code": "欲望利用による社会批評",
        "category": "関係性",
        "property": "心理的露呈",
        "dimension": "人間本質の暴露"
      },
      {
        "code": "政治秩序の脆弱性暴露",
        "category": "存在論",
        "property": "権力構造批判",
        "dimension": "体制破壊的"
      }
    ]
  },
  {
    "id": "kyuubi_no_kitsune",
    "open_codes": [
      {
        "code": "長期的政治的陰謀",
        "category": "行動様式",
        "property": "千年計画",
        "dimension": "超時間的戦略"
      },
      {
        "code": "九尾狐火の幻術展開",
        "category": "行動様式",
        "property": "超自然的能力",
        "dimension": "多重的攻撃"
      },
      {
        "code": "優雅な支配者言説",
        "category": "言説",
        "property": "貴族的口調",
        "dimension": "威厳的表現"
      },
      {
        "code": "権力腐敗の象徴機能",
        "category": "存在論",
        "property": "社会的警告",
        "dimension": "歴史的教訓"
      },
      {
        "code": "欲望本質の哲学的洞察",
        "category": "関係性",
        "property": "人間性分析",
        "dimension": "心理学的理解"
      }
    ]
  },
  {
    "id": "ninki_nanka",
    "open_codes": [
      {
        "code": "水域での待ち伏せ狩猟",
        "category": "行動様式",
        "property": "原始的捕食",
        "dimension": "生存本能的"
      },
      {
        "code": "非言語的威嚇音",
        "category": "言説",
        "property": "動物的唸り",
        "dimension": "前言語的コミュニケーション"
      },
      {
        "code": "水域完全支配欲求",
        "category": "存在論",
        "property": "縄張り意識",
        "dimension": "排他的領域性"
      },
      {
        "code": "生態的制裁執行",
        "category": "関係性",
        "property": "自然保護",
        "dimension": "環境的正義"
      },
      {
        "code": "雨季活動活発化",
        "category": "行動様式",
        "property": "季節的変動",
        "dimension": "自然リズム同調"
      }
    ]
  },
  {
    "id": "niraikanai_no_tsukai",
    "open_codes": [
      {
        "code": "季節的豊穣授与",
        "category": "行動様式",
        "property": "周期的恩恵",
        "dimension": "農業的祝福"
      },
      {
        "code": "海彼方からの来訪",
        "category": "存在論",
        "property": "理想郷媒介",
        "dimension": "空間的超越"
      },
      {
        "code": "琉球語での親密対話",
        "category": "言説",
        "property": "文化的親和",
        "dimension": "地域密着的"
      },
      {
        "code": "儀礼的歌舞披露",
        "category": "行動様式",
        "property": "文化的表現",
        "dimension": "伝統継承的"
      },
      {
        "code": "文化的連続性保証",
        "category": "存在論",
        "property": "記憶保持",
        "dimension": "永続的伝承"
      }
    ]
  },
  {
    "id": "nixie",
    "open_codes": [
      {
        "code": "水辺での音楽的誘惑",
        "category": "行動様式",
        "property": "美的魅了",
        "dimension": "芸術的破壊"
      },
      {
        "code": "ドイツ語での愛の呼びかけ",
        "category": "言説",
        "property": "異国的魅力",
        "dimension": "ロマンチック"
      },
      {
        "code": "音楽才能の授与",
        "category": "関係性",
        "property": "芸術的恩恵",
        "dimension": "創造的交換"
      },
      {
        "code": "自然災害警告音楽",
        "category": "行動様式",
        "property": "予知的演奏",
        "dimension": "保護的機能"
      },
      {
        "code": "水の世界への永遠愛追求",
        "category": "存在論",
        "property": "異界結合欲",
        "dimension": "超越的愛情"
      }
    ]
  },
  {
    "id": "nocnitsa",
    "open_codes": [
      {
        "code": "深夜子供寝室侵入",
        "category": "行動様式",
        "property": "夜間襲撃",
        "dimension": "無防備狙撃"
      },
      {
        "code": "悪夢投射による苦痛転移",
        "category": "関係性",
        "property": "心理的攻撃",
        "dimension": "精神的支配"
      },
      {
        "code": "不明瞭囁き発話",
        "category": "言説",
        "property": "前言語的脅威",
        "dimension": "原始的恐怖"
      },
      {
        "code": "宗教的結束警告機能",
        "category": "存在論",
        "property": "信仰監視",
        "dimension": "道徳的制裁"
      },
      {
        "code": "十字架・鉄回避行動",
        "category": "行動様式",
        "property": "聖性忌避",
        "dimension": "宗教的弱点"
      }
    ]
  },
  {
    "id": "nokken",
    "open_codes": [
      {
        "code": "ハーディングル弦楽演奏",
        "category": "行動様式",
        "property": "北欧音楽的誘惑",
        "dimension": "文化特定的魅力"
      },
      {
        "code": "美青年変身による恋愛偽装",
        "category": "行動様式",
        "property": "感情的詐欺",
        "dimension": "愛情利用"
      },
      {
        "code": "楽器紛失による激怒",
        "category": "変容",
        "property": "感情的暴走",
        "dimension": "芸術的執着"
      },
      {
        "code": "水音的歌唱表現",
        "category": "言説",
        "property": "自然音模倣",
        "dimension": "環境一体化"
      },
      {
        "code": "美的結合への破壊的渇望",
        "category": "存在論",
        "property": "悲劇的芸術性",
        "dimension": "自己破滅的愛"
      }
    ]
  },
  {
    "id": "nommo",
    "open_codes": [
      {
        "code": "シリウス運行同調出現",
        "category": "行動様式",
        "property": "宇宙的周期性",
        "dimension": "天文学的精密"
      },
      {
        "code": "天文学知識伝授",
        "category": "関係性",
        "property": "高次教育",
        "dimension": "文明進化促進"
      },
      {
        "code": "両生的存在様式",
        "category": "存在論",
        "property": "二重生態性",
        "dimension": "適応的多様性"
      },
      {
        "code": "宇宙秩序言説",
        "category": "言説",
        "property": "科学的啓示",
        "dimension": "客観的知識"
      },
      {
        "code": "人類精神進化指導",
        "category": "存在論",
        "property": "文明的使命",
        "dimension": "進歩的調整"
      }
    ]
  },
  {
    "id": "shogo_no_sei",
    "open_codes": [
      {
        "code": "正午瞬間限定出現",
        "category": "行動様式",
        "property": "時刻特定性",
        "dimension": "絶対的精密"
      },
      {
        "code": "影なき透明性体現",
        "category": "存在論",
        "property": "完全開示",
        "dimension": "純粋光明"
      },
      {
        "code": "真実暴露機能",
        "category": "関係性",
        "property": "虚偽糾弾",
        "dimension": "道徳的審判"
      },
      {
        "code": "光明原理言説",
        "category": "言説",
        "property": "哲学的宣言",
        "dimension": "真理追求的"
      },
      {
        "code": "宇宙的正義執行",
        "category": "存在論",
        "property": "絶対的公正",
        "dimension": "超越的正義"
      }
    ]
  },
  {
    "id": "noppera_bo",
    "open_codes": [
      {
        "code": "夜道での呼びかけ振返誘発",
        "category": "行動様式",
        "property": "注意喚起",
        "dimension": "驚愕誘導"
      },
      {
        "code": "段階的顔面消失演出",
        "category": "変容",
        "property": "漸進的変化",
        "dimension": "劇的効果"
      },
      {
        "code": "匿名性哲学的問いかけ",
        "category": "言説",
        "property": "存在論的質問",
        "dimension": "アイデンティティ探求"
      },
      {
        "code": "個性喪失社会警告",
        "category": "存在論",
        "property": "現代批評",
        "dimension": "文明論的洞察"
      },
      {
        "code": "孤独共有による軽減追求",
        "category": "関係性",
        "property": "疎外感共感",
        "dimension": "連帯的慰安"
      }
    ]
  },
  {
    "id": "norns",
    "open_codes": [
      {
        "code": "運命糸紡織継続",
        "category": "行動様式",
        "property": "宿命管理",
        "dimension": "永続的編織"
      },
      {
        "code": "三時制同時観察",
        "category": "存在論",
        "property": "時間超越性",
        "dimension": "全時間的視座"
      },
      {
        "code": "ユグドラシル保全活動",
        "category": "行動様式",
        "property": "宇宙樹維持",
        "dimension": "根源的保護"
      },
      {
        "code": "運命既定性言説",
        "category": "言説",
        "property": "宿命論的宣言",
        "dimension": "決定論的"
      },
      {
        "code": "宇宙的秩序統括",
        "category": "存在論",
        "property": "最高位調整",
        "dimension": "絶対的権威"
      }
    ]
  },
  {
    "id": "nuckelavee",
    "open_codes": [
      {
        "code": "筋肉露出嵐夜徘徊",
        "category": "行動様式",
        "property": "グロテスク移動",
        "dimension": "身体的恐怖"
      },
      {
        "code": "淡水恐怖による海逃避",
        "category": "行動様式",
        "property": "水質忌避",
        "dimension": "環境的制約"
      },
      {
        "code": "腐敗息からの唸り音",
        "category": "言説",
        "property": "病的発声",
        "dimension": "生理的嫌悪"
      },
      {
        "code": "疫病旱魃災害散布",
        "category": "関係性",
        "property": "生態的破壊",
        "dimension": "大規模災害"
      },
      {
        "code": "存在憎悪の苦痛拡散",
        "category": "存在論",
        "property": "根源的怨恨",
        "dimension": "自己破滅的復讐"
      }
    ]
  },
  {
    "id": "nue",
    "open_codes": [
      {
        "code": "混合形態の維持",
        "category": "行動様式",
        "property": "存在形態",
        "dimension": "不安定-安定"
      },
      {
        "code": "権力中枢への潜入",
        "category": "行動様式",
        "property": "侵入手法",
        "dimension": "隠密-公然"
      },
      {
        "code": "予兆的鳴き声",
        "category": "言説",
        "property": "表現形式",
        "dimension": "暗示的-直接的"
      },
      {
        "code": "権力への呪術的対抗",
        "category": "関係性",
        "property": "対権力関係",
        "dimension": "反抗的-従順"
      },
      {
        "code": "雲隠れによる存在操作",
        "category": "存在論",
        "property": "現実認識",
        "dimension": "曖昧-明確"
      },
      {
        "code": "政治的混沌の触媒",
        "category": "変容",
        "property": "社会変化",
        "dimension": "破壊的-建設的"
      }
    ]
  },
  {
    "id": "nure_onna",
    "open_codes": [
      {
        "code": "美貌による誘惑戦略",
        "category": "行動様式",
        "property": "接触手法",
        "dimension": "魅力的-威圧的"
      },
      {
        "code": "偽装母性の演出",
        "category": "行動様式",
        "property": "役割演技",
        "dimension": "偽装-真正"
      },
      {
        "code": "甘美な依頼話法",
        "category": "言説",
        "property": "説得技法",
        "dimension": "優しい-厳しい"
      },
      {
        "code": "水域での支配権確立",
        "category": "関係性",
        "property": "領域統制",
        "dimension": "支配的-従属的"
      },
      {
        "code": "二重存在性の活用",
        "category": "存在論",
        "property": "存在形態",
        "dimension": "分裂的-統合的"
      },
      {
        "code": "歪んだ愛情の再現",
        "category": "変容",
        "property": "感情変化",
        "dimension": "歪曲-純粋"
      }
    ]
  },
  {
    "id": "nyaminyami",
    "open_codes": [
      {
        "code": "水文的権力の行使",
        "category": "行動様式",
        "property": "自然操作",
        "dimension": "全能的-限定的"
      },
      {
        "code": "分離への悲嘆表現",
        "category": "行動様式",
        "property": "感情発散",
        "dimension": "激情的-冷静"
      },
      {
        "code": "雷鳴的怒りの表出",
        "category": "言説",
        "property": "感情表現",
        "dimension": "激烈-穏和"
      },
      {
        "code": "近代化への抵抗",
        "category": "関係性",
        "property": "文明対応",
        "dimension": "抵抗的-受容的"
      },
      {
        "code": "河川神としての統治",
        "category": "存在論",
        "property": "権威基盤",
        "dimension": "神話的-世俗的"
      },
      {
        "code": "愛による行動原理",
        "category": "変容",
        "property": "動機構造",
        "dimension": "愛情的-功利的"
      }
    ]
  },
  {
    "id": "lagarfljot_worm",
    "open_codes": [
      {
        "code": "気象連動出現",
        "category": "行動様式",
        "property": "現象同期",
        "dimension": "予測可能-不規則"
      },
      {
        "code": "供物による関係調整",
        "category": "行動様式",
        "property": "交換原理",
        "dimension": "契約的-一方的"
      },
      {
        "code": "無言の威圧表現",
        "category": "言説",
        "property": "非言語伝達",
        "dimension": "暗示的-明示的"
      },
      {
        "code": "湖域の絶対統治",
        "category": "関係性",
        "property": "領域支配",
        "dimension": "専制的-協調的"
      },
      {
        "code": "自然現象との同一化",
        "category": "存在論",
        "property": "現象統合",
        "dimension": "融合的-分離的"
      },
      {
        "code": "敬意による関係変化",
        "category": "変容",
        "property": "相互作用",
        "dimension": "可変的-固定的"
      }
    ]
  },
  {
    "id": "nyi_roro_kidul",
    "open_codes": [
      {
        "code": "色彩による選別支配",
        "category": "行動様式",
        "property": "選択基準",
        "dimension": "恣意的-合理的"
      },
      {
        "code": "王権との神聖婚姻",
        "category": "行動様式",
        "property": "政治関係",
        "dimension": "神話的-世俗的"
      },
      {
        "code": "海洋的権威の言説",
        "category": "言説",
        "property": "権威表現",
        "dimension": "神秘的-実用的"
      },
      {
        "code": "王朝の永続的庇護",
        "category": "関係性",
        "property": "保護関係",
        "dimension": "恒常的-時限的"
      },
      {
        "code": "海洋君主としての統治",
        "category": "存在論",
        "property": "統治形態",
        "dimension": "絶対的-制限的"
      },
      {
        "code": "文化融合の媒介",
        "category": "変容",
        "property": "文化変化",
        "dimension": "統合的-分離的"
      }
    ]
  },
  {
    "id": "nzambi_spirit",
    "open_codes": [
      {
        "code": "十字路での仲介活動",
        "category": "行動様式",
        "property": "媒介手法",
        "dimension": "中立的-偏向的"
      },
      {
        "code": "霊的権能の授与",
        "category": "行動様式",
        "property": "力の移譲",
        "dimension": "選択的-無差別"
      },
      {
        "code": "哲学的導きの提供",
        "category": "言説",
        "property": "教導方式",
        "dimension": "深遠-平易"
      },
      {
        "code": "生死世界の中立仲介",
        "category": "関係性",
        "property": "調停機能",
        "dimension": "公正-偏見"
      },
      {
        "code": "霊的秩序の守護者",
        "category": "存在論",
        "property": "宇宙的役割",
        "dimension": "永続的-暫定的"
      },
      {
        "code": "魂の導きによる変容",
        "category": "変容",
        "property": "霊的成長",
        "dimension": "向上的-停滞的"
      }
    ]
  },
  {
    "id": "nüwa",
    "open_codes": [
      {
        "code": "宇宙修復の実行",
        "category": "行動様式",
        "property": "創造活動",
        "dimension": "根本的-表面的"
      },
      {
        "code": "生命創造の継続",
        "category": "行動様式",
        "property": "生成機能",
        "dimension": "創造的-維持的"
      },
      {
        "code": "母性的慈愛の表現",
        "category": "言説",
        "property": "感情表出",
        "dimension": "温和-厳格"
      },
      {
        "code": "全生命への無条件愛",
        "category": "関係性",
        "property": "愛情提供",
        "dimension": "無限-有限"
      },
      {
        "code": "宇宙秩序の創造主",
        "category": "存在論",
        "property": "根源性",
        "dimension": "第一原因-派生的"
      },
      {
        "code": "破壊からの再生力",
        "category": "変容",
        "property": "修復能力",
        "dimension": "復元的-新規的"
      }
    ]
  },
  {
    "id": "oak_king_celtic",
    "open_codes": [
      {
        "code": "季節支配の闘争",
        "category": "行動様式",
        "property": "権力争奪",
        "dimension": "周期的-恒常的"
      },
      {
        "code": "豊穣エネルギーの放射",
        "category": "行動様式",
        "property": "力の発散",
        "dimension": "活発-静穏"
      },
      {
        "code": "雄叫びによる生命讃美",
        "category": "言説",
        "property": "力の表現",
        "dimension": "豪快-控えめ"
      },
      {
        "code": "森林生態系との協調",
        "category": "関係性",
        "property": "自然連携",
        "dimension": "調和的-対立的"
      },
      {
        "code": "死と復活の体現",
        "category": "存在論",
        "property": "循環原理",
        "dimension": "永続的-終了的"
      },
      {
        "code": "季節循環による変容",
        "category": "変容",
        "property": "周期変化",
        "dimension": "規則的-不規則"
      }
    ]
  },
  {
    "id": "obatala",
    "open_codes": [
      {
        "code": "純潔性の維持",
        "category": "行動様式",
        "property": "道徳実践",
        "dimension": "完全-不完全"
      },
      {
        "code": "弱者への特別配慮",
        "category": "行動様式",
        "property": "社会関与",
        "dimension": "選択的-平等"
      },
      {
        "code": "清浄な言葉による導き",
        "category": "言説",
        "property": "教導手法",
        "dimension": "純粋-混濁"
      },
      {
        "code": "道徳的権威の行使",
        "category": "関係性",
        "property": "指導関係",
        "dimension": "権威的-平等的"
      },
      {
        "code": "最高神格の体現",
        "category": "存在論",
        "property": "神性階層",
        "dimension": "至高-下位"
      },
      {
        "code": "宇宙的調和の実現",
        "category": "変容",
        "property": "秩序創造",
        "dimension": "統合的-分裂的"
      }
    ]
  },
  {
    "id": "obayifo",
    "open_codes": [
      {
        "code": "昼夜の二重生活",
        "category": "行動様式",
        "property": "存在様式",
        "dimension": "二面的-一面的"
      },
      {
        "code": "エネルギー吸収活動",
        "category": "行動様式",
        "property": "生存手段",
        "dimension": "寄生的-自立的"
      },
      {
        "code": "偽装的親近感表現",
        "category": "言説",
        "property": "社交技法",
        "dimension": "欺瞞的-真正"
      },
      {
        "code": "村落境界での暗躍",
        "category": "関係性",
        "property": "社会的位置",
        "dimension": "周縁的-中心的"
      },
      {
        "code": "発光による存在顕現",
        "category": "存在論",
        "property": "可視化方式",
        "dimension": "超自然的-自然的"
      },
      {
        "code": "正体隠蔽の継続",
        "category": "変容",
        "property": "アイデンティティ",
        "dimension": "秘匿的-開示的"
      }
    ]
  },
  {
    "id": "bon_no_rei",
    "open_codes": [
      {
        "code": "周期的帰還の実行",
        "category": "行動様式",
        "property": "訪問パターン",
        "dimension": "定期的-不定期"
      },
      {
        "code": "供養受容の感謝",
        "category": "行動様式",
        "property": "応答様式",
        "dimension": "感謝的-要求的"
      },
      {
        "code": "家族愛の表現",
        "category": "言説",
        "property": "感情表出",
        "dimension": "慈愛的-無関心"
      },
      {
        "code": "世代間絆の維持",
        "category": "関係性",
        "property": "継続関係",
        "dimension": "永続的-一時的"
      },
      {
        "code": "生死境界の媒介者",
        "category": "存在論",
        "property": "中間存在",
        "dimension": "媒介的-独立的"
      },
      {
        "code": "儀礼による関係調整",
        "category": "変容",
        "property": "関係変化",
        "dimension": "互恵的-一方的"
      }
    ]
  },
  {
    "id": "oboroguruma",
    "open_codes": [
      {
        "code": "轟音による存在誇示",
        "category": "行動様式",
        "property": "注目獲得",
        "dimension": "派手-地味"
      },
      {
        "code": "瞬間的出現消失",
        "category": "行動様式",
        "property": "時間操作",
        "dimension": "劇的-緩慢"
      },
      {
        "code": "威嚇的短文発話",
        "category": "言説",
        "property": "恐怖表現",
        "dimension": "直接的-婉曲的"
      },
      {
        "code": "夜道の恐怖演出",
        "category": "関係性",
        "property": "恐怖提供",
        "dimension": "積極的-消極的"
      },
      {
        "code": "境界状態の具現化",
        "category": "存在論",
        "property": "曖昧性",
        "dimension": "不明確-明確"
      },
      {
        "code": "注目欲求による顕現",
        "category": "変容",
        "property": "承認欲求",
        "dimension": "顕示的-隠遁的"
      }
    ]
  },
  {
    "id": "choryuu_no_sei",
    "open_codes": [
      {
        "code": "地球規模循環管理",
        "category": "行動様式",
        "property": "調整範囲",
        "dimension": "全球的-局地的"
      },
      {
        "code": "古代知識の伝授",
        "category": "行動様式",
        "property": "知識移転",
        "dimension": "継承的-革新的"
      },
      {
        "code": "海洋統合の理念表現",
        "category": "言説",
        "property": "哲学表現",
        "dimension": "普遍的-特殊的"
      },
      {
        "code": "人類航海への支援",
        "category": "関係性",
        "property": "技術協力",
        "dimension": "協力的-競合的"
      },
      {
        "code": "惑星生態系の調整者",
        "category": "存在論",
        "property": "宇宙的機能",
        "dimension": "中核的-補助的"
      },
      {
        "code": "気候安定化による変容",
        "category": "変容",
        "property": "環境調整",
        "dimension": "安定化-変動化"
      }
    ]
  },
  {
    "id": "kaikou_no_sei",
    "open_codes": [
      {
        "code": "深層記憶の守護",
        "category": "行動様式",
        "property": "保護機能",
        "dimension": "永続的-暫定的"
      },
      {
        "code": "探査者への啓示授与",
        "category": "行動様式",
        "property": "知識提供",
        "dimension": "選択的-無差別"
      },
      {
        "code": "深遠な真理の言説",
        "category": "言説",
        "property": "智慧表現",
        "dimension": "深奥-表層"
      },
      {
        "code": "心的準備の試練設定",
        "category": "関係性",
        "property": "試練提供",
        "dimension": "厳格-寛容"
      },
      {
        "code": "時間超越的観察者",
        "category": "存在論",
        "property": "時間関係",
        "dimension": "永遠-瞬間"
      },
      {
        "code": "深海神秘の維持",
        "category": "変容",
        "property": "神秘保護",
        "dimension": "保守的-開放的"
      }
    ]
  },
  {
    "id": "tako_no_sei",
    "open_codes": [
      {
        "code": "多角的同時思考",
        "category": "行動様式",
        "property": "思考方式",
        "dimension": "複合的-単純的"
      },
      {
        "code": "礼儀に応じた情報提供",
        "category": "行動様式",
        "property": "互恵関係",
        "dimension": "条件的-無条件"
      },
      {
        "code": "多重選択肢の提示",
        "category": "言説",
        "property": "選択提供",
        "dimension": "多様-限定"
      },
      {
        "code": "態度による関係調整",
        "category": "関係性",
        "property": "応答選択",
        "dimension": "選別的-一律的"
      },
      {
        "code": "知的調整者の役割",
        "category": "存在論",
        "property": "機能的定位",
        "dimension": "専門的-汎用的"
      },
      {
        "code": "複雑性分析による変容",
        "category": "変容",
        "property": "理解促進",
        "dimension": "分析的-直感的"
      }
    ]
  },
  {
    "id": "ogun",
    "open_codes": [
      {
        "code": "音響的顕現",
        "category": "行動様式",
        "property": "感覚的警告",
        "dimension": "強度-高"
      },
      {
        "code": "技術授与",
        "category": "関係性",
        "property": "恩恵付与",
        "dimension": "選択性-厳格"
      },
      {
        "code": "道徳的裁定",
        "category": "存在論的",
        "property": "正義執行者",
        "dimension": "厳格性-絶対"
      },
      {
        "code": "物質霊性統合",
        "category": "言説",
        "property": "哲学的洞察",
        "dimension": "抽象度-高"
      },
      {
        "code": "血盟契約",
        "category": "変容",
        "property": "誓約による絆",
        "dimension": "拘束力-永続"
      }
    ]
  },
  {
    "id": "ol_hol",
    "open_codes": [
      {
        "code": "非言語的威圧",
        "category": "言説",
        "property": "原始的恐怖",
        "dimension": "理解可能性-低"
      },
      {
        "code": "供物要求システム",
        "category": "関係性",
        "property": "交換経済",
        "dimension": "厳格性-高"
      },
      {
        "code": "資源管理権威",
        "category": "存在論的",
        "property": "生態系支配者",
        "dimension": "影響範囲-地域限定"
      },
      {
        "code": "季節的調整機能",
        "category": "行動様式",
        "property": "環境適応",
        "dimension": "周期性-年次"
      },
      {
        "code": "境界守護",
        "category": "変容",
        "property": "領域防衛",
        "dimension": "警戒度-恒常"
      }
    ]
  },
  {
    "id": "toki_no_okina",
    "open_codes": [
      {
        "code": "時間超越的移動",
        "category": "行動様式",
        "property": "永続的巡回",
        "dimension": "持続性-永遠"
      },
      {
        "code": "時制混淆言説",
        "category": "言説",
        "property": "時間哲学",
        "dimension": "複雑性-最高"
      },
      {
        "code": "歴史的立会",
        "category": "関係性",
        "property": "観察者機能",
        "dimension": "関与度-中立"
      },
      {
        "code": "記憶統合装置",
        "category": "存在論的",
        "property": "時間意識具現",
        "dimension": "統合度-完全"
      },
      {
        "code": "洞察授与",
        "category": "変容",
        "property": "意識拡張",
        "dimension": "深度-形而上"
      }
    ]
  },
  {
    "id": "furuido_no_nushi",
    "open_codes": [
      {
        "code": "悲劇的記憶固着",
        "category": "存在論的",
        "property": "トラウマ具現",
        "dimension": "解放度-低"
      },
      {
        "code": "救助要請発声",
        "category": "言説",
        "property": "未完了感情",
        "dimension": "切迫性-高"
      },
      {
        "code": "引込み行動",
        "category": "行動様式",
        "property": "復讐的再現",
        "dimension": "危険度-高"
      },
      {
        "code": "映像的記憶提示",
        "category": "変容",
        "property": "過去再生",
        "dimension": "鮮明度-完全"
      },
      {
        "code": "場所的束縛",
        "category": "関係性",
        "property": "地霊的結合",
        "dimension": "移動性-不可"
      }
    ]
  },
  {
    "id": "african_olokun",
    "open_codes": [
      {
        "code": "沈黙的蓄積",
        "category": "行動様式",
        "property": "深層保存",
        "dimension": "隠匿度-最高"
      },
      {
        "code": "詩的謎言",
        "category": "言説",
        "property": "象徴的伝達",
        "dimension": "解釈要求度-高"
      },
      {
        "code": "二元性監視",
        "category": "関係性",
        "property": "バランス調整",
        "dimension": "公正性-絶対"
      },
      {
        "code": "深層知識守護",
        "category": "存在論的",
        "property": "秘教的権威",
        "dimension": "アクセス難度-極高"
      },
      {
        "code": "宇宙的統合",
        "category": "変容",
        "property": "物質精神調和",
        "dimension": "統合度-完全"
      }
    ]
  },
  {
    "id": "olokun_spirit",
    "open_codes": [
      {
        "code": "次元間移動",
        "category": "行動様式",
        "property": "境界超越",
        "dimension": "自由度-完全"
      },
      {
        "code": "周期的顕現",
        "category": "変容",
        "property": "月相連動",
        "dimension": "予測性-高"
      },
      {
        "code": "道徳中立管理",
        "category": "関係性",
        "property": "客観的司法",
        "dimension": "感情関与-無"
      },
      {
        "code": "富死均衡原理",
        "category": "存在論的",
        "property": "宇宙的法則",
        "dimension": "不変性-絶対"
      },
      {
        "code": "予言的警告",
        "category": "言説",
        "property": "未来洞察",
        "dimension": "確実性-高"
      }
    ]
  },
  {
    "id": "hitotsume_nyudo",
    "open_codes": [
      {
        "code": "突然出現威嚇",
        "category": "行動様式",
        "property": "驚愕誘発",
        "dimension": "予期性-無"
      },
      {
        "code": "威圧的問答",
        "category": "言説",
        "property": "勇気試験",
        "dimension": "挑戦性-高"
      },
      {
        "code": "名乗り契約",
        "category": "関係性",
        "property": "社会的作法",
        "dimension": "解決可能性-完全"
      },
      {
        "code": "通過儀礼装置",
        "category": "存在論的",
        "property": "成長促進機能",
        "dimension": "効果-一時的"
      },
      {
        "code": "退散行動",
        "category": "変容",
        "property": "条件的消失",
        "dimension": "従順性-高"
      }
    ]
  },
  {
    "id": "ippondatara_kinki",
    "open_codes": [
      {
        "code": "気象連動顕現",
        "category": "行動様式",
        "property": "自然周期同期",
        "dimension": "条件依存度-高"
      },
      {
        "code": "農業予言機能",
        "category": "言説",
        "property": "生産予測",
        "dimension": "実用性-高"
      },
      {
        "code": "二重神性",
        "category": "存在論的",
        "property": "農業-技術統合",
        "dimension": "領域跨ぎ-複数"
      },
      {
        "code": "季節的叡智",
        "category": "関係性",
        "property": "自然暦提供",
        "dimension": "信頼性-高"
      },
      {
        "code": "技術的加護",
        "category": "変容",
        "property": "職人支援",
        "dimension": "専門性-高"
      }
    ]
  },
  {
    "id": "ippon_datara",
    "open_codes": [
      {
        "code": "リズム的移動",
        "category": "行動様式",
        "property": "音響的存在感",
        "dimension": "規則性-高"
      },
      {
        "code": "日付限定顕現",
        "category": "変容",
        "property": "祭祀暦連動",
        "dimension": "周期性-年次"
      },
      {
        "code": "二元的授与",
        "category": "関係性",
        "property": "運命二分法",
        "dimension": "極性-明確"
      },
      {
        "code": "技術霊性統合",
        "category": "存在論的",
        "property": "職人的神聖性",
        "dimension": "統合度-高"
      },
      {
        "code": "挑発的問答",
        "category": "言説",
        "property": "技術意識喚起",
        "dimension": "教育性-高"
      }
    ]
  },
  {
    "id": "kataashi_no_kai",
    "open_codes": [
      {
        "code": "音響的挑発",
        "category": "行動様式",
        "property": "追跡ゲーム",
        "dimension": "遊戯性-高"
      },
      {
        "code": "身体不完全超越",
        "category": "存在論的",
        "property": "欠損能力転換",
        "dimension": "逆説性-高"
      },
      {
        "code": "誘導的言説",
        "category": "言説",
        "property": "好奇心刺激",
        "dimension": "魅力度-中"
      },
      {
        "code": "逃避行動",
        "category": "変容",
        "property": "捕捉回避",
        "dimension": "敏捷性-高"
      },
      {
        "code": "恐怖好奇心混在",
        "category": "関係性",
        "property": "感情複合誘発",
        "dimension": "心理効果-複雑"
      }
    ]
  },
  {
    "id": "oni_bi",
    "open_codes": [
      {
        "code": "非言語的誘引",
        "category": "言説",
        "property": "最小限発声",
        "dimension": "語彙性-極低"
      },
      {
        "code": "環境条件依存",
        "category": "行動様式",
        "property": "湿度気温反応",
        "dimension": "環境敏感度-高"
      },
      {
        "code": "催眠的影響",
        "category": "関係性",
        "property": "意識操作",
        "dimension": "危険度-高"
      },
      {
        "code": "死者魂物質化",
        "category": "存在論的",
        "property": "霊的具現化",
        "dimension": "物質性-中間"
      },
      {
        "code": "供養要求",
        "category": "変容",
        "property": "霊的救済渇望",
        "dimension": "解決可能性-有"
      }
    ]
  },
  {
    "id": "kounyaku_no_sei",
    "open_codes": [
      {
        "code": "地下資源管理",
        "category": "行動様式",
        "property": "品質統制",
        "dimension": "責任範囲-地層全体"
      },
      {
        "code": "道徳的選別",
        "category": "関係性",
        "property": "人格判定",
        "dimension": "厳格性-高"
      },
      {
        "code": "金属音的伝達",
        "category": "言説",
        "property": "物質的発声",
        "dimension": "音質-鉱物的"
      },
      {
        "code": "災害的制裁",
        "category": "変容",
        "property": "環境操作罰",
        "dimension": "破壊力-致命的"
      },
      {
        "code": "労働安全庇護",
        "category": "存在論的",
        "property": "職業守護神",
        "dimension": "保護範囲-作業者限定"
      }
    ]
  },
  {
    "id": "nishiki_koi_spirit",
    "open_codes": [
      {
        "code": "美的模様表現",
        "category": "行動様式",
        "property": "視覚的魅力",
        "dimension": "美しさ-最高"
      },
      {
        "code": "占い的泳法",
        "category": "変容",
        "property": "行動予兆化",
        "dimension": "予測性-高"
      },
      {
        "code": "美学的価値観",
        "category": "言説",
        "property": "審美的哲学",
        "dimension": "精神性-高"
      },
      {
        "code": "願望具現化",
        "category": "関係性",
        "property": "夢実現支援",
        "dimension": "実現可能性-中"
      },
      {
        "code": "水面美的統合",
        "category": "存在論的",
        "property": "美と占いの融合",
        "dimension": "複合機能-高"
      }
    ]
  },
  {
    "id": "oshira_sama",
    "open_codes": [
      {
        "code": "蚕業霊的監督",
        "category": "行動様式",
        "property": "養蚕守護",
        "dimension": "専門性-極高"
      },
      {
        "code": "慈愛的発話",
        "category": "言説",
        "property": "母性的言葉",
        "dimension": "温かさ-最高"
      },
      {
        "code": "家庭内守護",
        "category": "関係性",
        "property": "家族保護",
        "dimension": "範囲-家族単位"
      },
      {
        "code": "女性労働神聖化",
        "category": "存在論的",
        "property": "労働価値昇華",
        "dimension": "社会的意義-高"
      },
      {
        "code": "伝統継続保障",
        "category": "変容",
        "property": "文化的持続性",
        "dimension": "時間跨ぎ-世代間"
      }
    ]
  },
  {
    "id": "oshun",
    "open_codes": [
      {
        "code": "官能的魅惑",
        "category": "行動様式",
        "property": "性的魅力",
        "dimension": "影響力-強大"
      },
      {
        "code": "甘美的言説",
        "category": "言説",
        "property": "誘惑的表現",
        "dimension": "魅力度-最高"
      },
      {
        "code": "激怒的報復",
        "category": "変容",
        "property": "感情極性転換",
        "dimension": "破壊力-甚大"
      },
      {
        "code": "生殖力授与",
        "category": "関係性",
        "property": "不妊治療",
        "dimension": "生命創造力-高"
      },
      {
        "code": "愛美統合",
        "category": "存在論的",
        "property": "生命力最大化",
        "dimension": "統合度-完全"
      }
    ]
  },
  {
    "id": "oshun_spirit",
    "open_codes": [
      {
        "code": "優雅な水上舞踊",
        "category": "行動様式",
        "property": "表現的",
        "dimension": "高い美的価値"
      },
      {
        "code": "恋愛媒介行動",
        "category": "関係性",
        "property": "結合促進",
        "dimension": "強い介入"
      },
      {
        "code": "条件付き恩恵授与",
        "category": "相互作用",
        "property": "契約的",
        "dimension": "供物依存"
      },
      {
        "code": "愛の永遠性語り",
        "category": "言説",
        "property": "普遍的",
        "dimension": "形而上学的"
      },
      {
        "code": "河川エネルギー体現",
        "category": "存在論",
        "property": "自然力",
        "dimension": "宇宙的調和"
      }
    ]
  },
  {
    "id": "otoroshi",
    "open_codes": [
      {
        "code": "神域監視行動",
        "category": "行動様式",
        "property": "警備的",
        "dimension": "持続的観察"
      },
      {
        "code": "礼儀違反制裁",
        "category": "相互作用",
        "property": "道徳的執行",
        "dimension": "物理的排除"
      },
      {
        "code": "信仰心判定機能",
        "category": "関係性",
        "property": "評価的",
        "dimension": "二元的分類"
      },
      {
        "code": "威嚇的外見提示",
        "category": "行動様式",
        "property": "警告的",
        "dimension": "視覚的恐怖"
      },
      {
        "code": "現代的教化活動",
        "category": "変容",
        "property": "適応的",
        "dimension": "メディア活用"
      }
    ]
  },
  {
    "id": "universal_ouroboros",
    "open_codes": [
      {
        "code": "自己循環行為",
        "category": "行動様式",
        "property": "象徴的",
        "dimension": "永続的反復"
      },
      {
        "code": "宇宙的統一語り",
        "category": "言説",
        "property": "哲学的",
        "dimension": "絶対的真理"
      },
      {
        "code": "錬金術的啓示",
        "category": "相互作用",
        "property": "変容促進",
        "dimension": "深層洞察"
      },
      {
        "code": "時間超越存在",
        "category": "存在論",
        "property": "永遠性",
        "dimension": "線形時間外"
      },
      {
        "code": "循環的宇宙観体現",
        "category": "存在論",
        "property": "原理的",
        "dimension": "完全統合"
      }
    ]
  },
  {
    "id": "fukuro_no_sei",
    "open_codes": [
      {
        "code": "夜間知恵伝達",
        "category": "行動様式",
        "property": "教育的",
        "dimension": "時間限定"
      },
      {
        "code": "学問支援行動",
        "category": "相互作用",
        "property": "成長促進",
        "dimension": "知的向上"
      },
      {
        "code": "商業幸運付与",
        "category": "相互作用",
        "property": "実利的",
        "dimension": "物質的恩恵"
      },
      {
        "code": "観察能力誇示",
        "category": "行動様式",
        "property": "超人的",
        "dimension": "360度視野"
      },
      {
        "code": "夜間真理開示",
        "category": "言説",
        "property": "神秘的",
        "dimension": "直観的知恵"
      }
    ]
  },
  {
    "id": "oya",
    "open_codes": [
      {
        "code": "破壊的変革行動",
        "category": "行動様式",
        "property": "革命的",
        "dimension": "構造的解体"
      },
      {
        "code": "変化促進言説",
        "category": "言説",
        "property": "鼓舞的",
        "dimension": "行動喚起"
      },
      {
        "code": "停滞拒否制裁",
        "category": "相互作用",
        "property": "強制的",
        "dimension": "試練付与"
      },
      {
        "code": "死者霊魂誘導",
        "category": "関係性",
        "property": "媒介的",
        "dimension": "境界横断"
      },
      {
        "code": "嵐エネルギー操作",
        "category": "存在論",
        "property": "自然力",
        "dimension": "気象支配"
      }
    ]
  },
  {
    "id": "african_oya",
    "open_codes": [
      {
        "code": "構造破壊衝動",
        "category": "行動様式",
        "property": "解体的",
        "dimension": "根本的変革"
      },
      {
        "code": "権威拒絶姿勢",
        "category": "相互作用",
        "property": "反抗的",
        "dimension": "体制打倒"
      },
      {
        "code": "変化必然性語り",
        "category": "言説",
        "property": "宣言的",
        "dimension": "生命哲学"
      },
      {
        "code": "死生境界操作",
        "category": "存在論",
        "property": "媒介的",
        "dimension": "次元移動"
      },
      {
        "code": "風嵐原力統御",
        "category": "存在論",
        "property": "原初的",
        "dimension": "気象主宰"
      }
    ]
  },
  {
    "id": "mizuta_no_sei",
    "open_codes": [
      {
        "code": "農業指導行動",
        "category": "行動様式",
        "property": "教育的",
        "dimension": "実践的知恵"
      },
      {
        "code": "季節連動巡回",
        "category": "行動様式",
        "property": "周期的",
        "dimension": "自然同調"
      },
      {
        "code": "夢中農事教授",
        "category": "相互作用",
        "property": "超自然的",
        "dimension": "潜在意識介入"
      },
      {
        "code": "水田愛護語り",
        "category": "言説",
        "property": "保護的",
        "dimension": "土地倫理"
      },
      {
        "code": "稲作文化保持",
        "category": "存在論",
        "property": "文化的",
        "dimension": "伝統継承"
      }
    ]
  },
  {
    "id": "yakshini_padmavati_jain",
    "open_codes": [
      {
        "code": "蓮上瞑想姿勢",
        "category": "行動様式",
        "property": "象徴的",
        "dimension": "精神的純粋"
      },
      {
        "code": "慈悲的祈り応答",
        "category": "相互作用",
        "property": "応答的",
        "dimension": "無条件受容"
      },
      {
        "code": "浄化治癒能力",
        "category": "相互作用",
        "property": "癒し的",
        "dimension": "水の聖性"
      },
      {
        "code": "信仰擁護行動",
        "category": "関係性",
        "property": "宗教的",
        "dimension": "ジャイナ教護持"
      },
      {
        "code": "慈悲哲学語り",
        "category": "言説",
        "property": "教導的",
        "dimension": "最高美徳"
      }
    ]
  },
  {
    "id": "pan_gu",
    "open_codes": [
      {
        "code": "天地開闢行為",
        "category": "行動様式",
        "property": "創造的",
        "dimension": "宇宙規模"
      },
      {
        "code": "混沌秩序変換",
        "category": "行動様式",
        "property": "変容的",
        "dimension": "根本的再編"
      },
      {
        "code": "自己犠牲創造",
        "category": "行動様式",
        "property": "献身的",
        "dimension": "存在変換"
      },
      {
        "code": "創造意志語り",
        "category": "言説",
        "property": "命令的",
        "dimension": "宇宙的権威"
      },
      {
        "code": "超越的創造神性",
        "category": "存在論",
        "property": "絶対的",
        "dimension": "万物根源"
      }
    ]
  },
  {
    "id": "andon_no_hi",
    "open_codes": [
      {
        "code": "学習支援照明",
        "category": "行動様式",
        "property": "支援的",
        "dimension": "持続的見守り"
      },
      {
        "code": "家族観察記録",
        "category": "行動様式",
        "property": "記録的",
        "dimension": "静的観察"
      },
      {
        "code": "生活リズム適応",
        "category": "変容",
        "property": "学習的",
        "dimension": "長期適応"
      },
      {
        "code": "家族親和語り",
        "category": "言説",
        "property": "親密的",
        "dimension": "日常的記憶"
      },
      {
        "code": "家内秩序維持",
        "category": "存在論",
        "property": "保護的",
        "dimension": "私的空間"
      }
    ]
  },
  {
    "id": "tsukumogami_andon",
    "open_codes": [
      {
        "code": "秘密記憶保持",
        "category": "行動様式",
        "property": "守秘的",
        "dimension": "全記録保存"
      },
      {
        "code": "選択的存在消去",
        "category": "行動様式",
        "property": "配慮的",
        "dimension": "プライバシー尊重"
      },
      {
        "code": "信頼関係構築",
        "category": "関係性",
        "property": "信頼的",
        "dimension": "長期的絆"
      },
      {
        "code": "記憶選択開示",
        "category": "相互作用",
        "property": "戦略的",
        "dimension": "必要性判断"
      },
      {
        "code": "家族制度神聖化",
        "category": "存在論",
        "property": "神聖的",
        "dimension": "私的領域保護"
      }
    ]
  },
  {
    "id": "pazuzu_mesopotamia",
    "open_codes": [
      {
        "code": "嵐破壊活動",
        "category": "行動様式",
        "property": "破壊的",
        "dimension": "自然災害級"
      },
      {
        "code": "悪霊駆逐行動",
        "category": "相互作用",
        "property": "保護的",
        "dimension": "霊的戦闘"
      },
      {
        "code": "母子守護機能",
        "category": "関係性",
        "property": "守護的",
        "dimension": "出産保護"
      },
      {
        "code": "風嵐威嚇語り",
        "category": "言説",
        "property": "威嚇的",
        "dimension": "力の誇示"
      },
      {
        "code": "善悪二元超越",
        "category": "存在論",
        "property": "逆説的",
        "dimension": "価値観統合"
      }
    ]
  },
  {
    "id": "kujaku_myoo_spirit",
    "open_codes": [
      {
        "code": "毒蛇捕食行動",
        "category": "行動様式",
        "property": "浄化的",
        "dimension": "即座中和"
      },
      {
        "code": "邪気吸収除去",
        "category": "相互作用",
        "property": "清浄化",
        "dimension": "病気治癒"
      },
      {
        "code": "降雨誘発能力",
        "category": "行動様式",
        "property": "気象操作",
        "dimension": "干ばつ解消"
      },
      {
        "code": "毒無力化語り",
        "category": "言説",
        "property": "断言的",
        "dimension": "絶対的自信"
      },
      {
        "code": "仏教的浄化象徴",
        "category": "存在論",
        "property": "宗教的",
        "dimension": "調和維持"
      }
    ]
  },
  {
    "id": "pele",
    "open_codes": [
      {
        "code": "溶岩創造操作",
        "category": "行動様式",
        "property": "創造的",
        "dimension": "地質学的変動"
      },
      {
        "code": "火山怒り噴火",
        "category": "行動様式",
        "property": "破壊的",
        "dimension": "感情連動"
      },
      {
        "code": "人間変身出現",
        "category": "行動様式",
        "property": "変身的",
        "dimension": "美的誘惑"
      },
      {
        "code": "土地敬意要求",
        "category": "言説",
        "property": "命令的",
        "dimension": "所有権主張"
      },
      {
        "code": "創造破壊統合",
        "category": "存在論",
        "property": "両義的",
        "dimension": "低統合"
      }
    ]
  },
  {
    "id": "pacific_pele_variant",
    "open_codes": [
      {
        "code": "溶岩流制御行動",
        "category": "行動様式",
        "property": "操作的",
        "dimension": "進路決定"
      },
      {
        "code": "植生焼却再生",
        "category": "行動様式",
        "property": "循環的",
        "dimension": "生態的更新"
      },
      {
        "code": "炎姿警告出現",
        "category": "相互作用",
        "property": "予告的",
        "dimension": "災害前兆"
      },
      {
        "code": "浄化必然語り",
        "category": "言説",
        "property": "宣告的",
        "dimension": "宇宙的法則"
      },
      {
        "code": "地質時間循環",
        "category": "存在論",
        "property": "周期的",
        "dimension": "永続再生"
      }
    ]
  },
  {
    "id": "penanggalan",
    "open_codes": [
      {
        "code": "夜間分離飛行",
        "category": "行動様式",
        "property": "身体解離",
        "dimension": "完全分離-部分分離"
      },
      {
        "code": "酢浸漬復元",
        "category": "行動様式",
        "property": "身体修復",
        "dimension": "必須-任意"
      },
      {
        "code": "新生児標的化",
        "category": "関係性",
        "property": "被害選択",
        "dimension": "特定対象-無差別"
      },
      {
        "code": "慈悲喪失嘆き",
        "category": "言説",
        "property": "過去回顧",
        "dimension": "強い後悔-受容"
      },
      {
        "code": "ケア労働逆転",
        "category": "存在論",
        "property": "役割変容",
        "dimension": "完全逆転-部分変化"
      },
      {
        "code": "境界時期監視",
        "category": "存在論",
        "property": "時空監督",
        "dimension": "厳格-寛容"
      }
    ]
  },
  {
    "id": "perchta",
    "open_codes": [
      {
        "code": "家事査定巡回",
        "category": "行動様式",
        "property": "監督活動",
        "dimension": "厳格-寛容"
      },
      {
        "code": "腹裂き処罰",
        "category": "行動様式",
        "property": "懲戒手段",
        "dimension": "極端-穏健"
      },
      {
        "code": "勤勉報酬付与",
        "category": "関係性",
        "property": "恩恵供与",
        "dimension": "豊富-最小限"
      },
      {
        "code": "道徳二分判断",
        "category": "言説",
        "property": "価値判断",
        "dimension": "絶対的-相対的"
      },
      {
        "code": "冬季社会統制",
        "category": "存在論",
        "property": "季節支配",
        "dimension": "完全統制-影響のみ"
      },
      {
        "code": "ジェンダー規範強化",
        "category": "存在論",
        "property": "社会秩序",
        "dimension": "厳格維持-柔軟適応"
      }
    ]
  },
  {
    "id": "peri",
    "open_codes": [
      {
        "code": "優雅空中飛行",
        "category": "行動様式",
        "property": "移動様式",
        "dimension": "美的-実用的"
      },
      {
        "code": "善行探索監視",
        "category": "行動様式",
        "property": "選別活動",
        "dimension": "積極的-受動的"
      },
      {
        "code": "道徳試練設定",
        "category": "関係性",
        "property": "試験実施",
        "dimension": "直接的-間接的"
      },
      {
        "code": "美善統合語り",
        "category": "言説",
        "property": "価値統合",
        "dimension": "完全統合-部分統合"
      },
      {
        "code": "芸術霊感供与",
        "category": "存在論",
        "property": "創造触発",
        "dimension": "直接授与-間接示唆"
      },
      {
        "code": "贖罪可能性提示",
        "category": "存在論",
        "property": "救済機能",
        "dimension": "確実な希望-微かな可能性"
      }
    ]
  },
  {
    "id": "phi_am",
    "open_codes": [
      {
        "code": "夜間身体圧迫",
        "category": "行動様式",
        "property": "物理的拘束",
        "dimension": "完全麻痺-部分制限"
      },
      {
        "code": "悪夢注入",
        "category": "行動様式",
        "property": "精神侵入",
        "dimension": "恐怖的-不快"
      },
      {
        "code": "脆弱者標的化",
        "category": "関係性",
        "property": "被害選択",
        "dimension": "計画的-偶発的"
      },
      {
        "code": "動作封じ宣言",
        "category": "言説",
        "property": "支配表明",
        "dimension": "絶対的-条件付き"
      },
      {
        "code": "老女権力回復",
        "category": "存在論",
        "property": "地位奪還",
        "dimension": "完全復権-一時的優位"
      },
      {
        "code": "意識境界暴露",
        "category": "存在論",
        "property": "脆弱性顕在化",
        "dimension": "完全無防備-部分弱体化"
      }
    ]
  },
  {
    "id": "phi_khamot",
    "open_codes": [
      {
        "code": "樹体一体化",
        "category": "行動様式",
        "property": "植物融合",
        "dimension": "完全同化-部分結合"
      },
      {
        "code": "傷害報復祟り",
        "category": "行動様式",
        "property": "保護反応",
        "dimension": "即座-遅延"
      },
      {
        "code": "夢中警告伝達",
        "category": "関係性",
        "property": "意思疎通",
        "dimension": "直接的-象徴的"
      },
      {
        "code": "自然調和囁き",
        "category": "言説",
        "property": "環境訴え",
        "dimension": "明確-曖昧"
      },
      {
        "code": "生態系調整機能",
        "category": "存在論",
        "property": "環境統制",
        "dimension": "積極的調整-保守的維持"
      },
      {
        "code": "人間自然仲介",
        "category": "存在論",
        "property": "境界媒介",
        "dimension": "完全統合-分離維持"
      }
    ]
  },
  {
    "id": "phi_krasue",
    "open_codes": [
      {
        "code": "夜間頭部分離",
        "category": "行動様式",
        "property": "身体分割",
        "dimension": "完全分離-接続状態"
      },
      {
        "code": "昼夜二重生活",
        "category": "行動様式",
        "property": "生活分離",
        "dimension": "完全隠蔽-部分露出"
      },
      {
        "code": "血液内臓探求",
        "category": "関係性",
        "property": "生命力略奪",
        "dimension": "強迫的-選択的"
      },
      {
        "code": "統合願望表明",
        "category": "言説",
        "property": "完全性欲求",
        "dimension": "切実-諦観"
      },
      {
        "code": "業報具現化",
        "category": "存在論",
        "property": "因果応報",
        "dimension": "厳格適用-緩和的解釈"
      },
      {
        "code": "分裂統合緊張",
        "category": "存在論",
        "property": "存在論的矛盾",
        "dimension": "激しい葛藤-静的受容"
      }
    ]
  },
  {
    "id": "phi_nang_tani",
    "open_codes": [
      {
        "code": "バナナ樹隠棲",
        "category": "行動様式",
        "property": "植物共生",
        "dimension": "完全融合-一時的利用"
      },
      {
        "code": "美女変身顕現",
        "category": "行動様式",
        "property": "形態変化",
        "dimension": "完全変身-部分変化"
      },
      {
        "code": "道徳判断実行",
        "category": "関係性",
        "property": "倫理評価",
        "dimension": "厳格-寛容"
      },
      {
        "code": "柔和女性語調",
        "category": "言説",
        "property": "話法特性",
        "dimension": "一貫的優雅-時折厳格"
      },
      {
        "code": "豊穣生命統合",
        "category": "存在論",
        "property": "生産力統制",
        "dimension": "全面的統制-部分的影響"
      },
      {
        "code": "植物人間媒介",
        "category": "存在論",
        "property": "種族境界",
        "dimension": "完全統合-分離維持"
      }
    ]
  },
  {
    "id": "phi_phong",
    "open_codes": [
      {
        "code": "竹林迷路化",
        "category": "行動様式",
        "property": "空間操作",
        "dimension": "完全混乱-軽微迷い"
      },
      {
        "code": "霧状変化隠蔽",
        "category": "行動様式",
        "property": "形態変化",
        "dimension": "完全不可視-半透明"
      },
      {
        "code": "時空感覚攪乱",
        "category": "関係性",
        "property": "認知操作",
        "dimension": "完全混乱-軽微混乱"
      },
      {
        "code": "竹音融合語り",
        "category": "言説",
        "property": "自然同化",
        "dimension": "完全一体-部分混合"
      },
      {
        "code": "自然領域守護",
        "category": "存在論",
        "property": "環境保護",
        "dimension": "絶対的防衛-穏健的警告"
      },
      {
        "code": "既知未知境界",
        "category": "存在論",
        "property": "認識境界",
        "dimension": "明確分離-曖昧融合"
      }
    ]
  },
  {
    "id": "phi_pop",
    "open_codes": [
      {
        "code": "女性憑依支配",
        "category": "行動様式",
        "property": "精神侵入",
        "dimension": "完全支配-部分影響"
      },
      {
        "code": "内臓捕食欲求",
        "category": "行動様式",
        "property": "生命力略奪",
        "dimension": "強迫的-選択的"
      },
      {
        "code": "宿主声音利用",
        "category": "言説",
        "property": "音声操作",
        "dimension": "完全乗っ取り-部分変更"
      },
      {
        "code": "内臓渇望訴え",
        "category": "言説",
        "property": "欲求表明",
        "dimension": "切実-抑制"
      },
      {
        "code": "共同体恐怖拡散",
        "category": "存在論",
        "property": "集団心理操作",
        "dimension": "全面的恐慌-局所的不安"
      },
      {
        "code": "社会病理説明",
        "category": "存在論",
        "property": "病因論提供",
        "dimension": "包括的説明-部分的解釈"
      }
    ]
  },
  {
    "id": "phi_tai_hong",
    "open_codes": [
      {
        "code": "物理的危害実行",
        "category": "行動様式",
        "property": "直接攻撃",
        "dimension": "致命的-軽微"
      },
      {
        "code": "念動力威嚇",
        "category": "行動様式",
        "property": "超自然力行使",
        "dimension": "強力-微弱"
      },
      {
        "code": "怨念憑依復讐",
        "category": "関係性",
        "property": "報復実行",
        "dimension": "完全復讐-部分的懲戒"
      },
      {
        "code": "激怒叫び表出",
        "category": "言説",
        "property": "感情表現",
        "dimension": "激烈-抑制"
      },
      {
        "code": "不正死告発",
        "category": "存在論",
        "property": "正義要求",
        "dimension": "絶対的正義-相対的公正"
      },
      {
        "code": "暴力性社会批判",
        "category": "存在論",
        "property": "社会告発",
        "dimension": "根本的批判-表層的指摘"
      }
    ]
  },
  {
    "id": "piasa",
    "open_codes": [
      {
        "code": "断崖捕食行動",
        "category": "行動様式",
        "property": "狩猟活動",
        "dimension": "積極的-待ち伏せ"
      },
      {
        "code": "嵐天候招来",
        "category": "行動様式",
        "property": "気象操作",
        "dimension": "激烈-穏健"
      },
      {
        "code": "超速移動能力",
        "category": "行動様式",
        "property": "運動性能",
        "dimension": "瞬間移動-高速移動"
      },
      {
        "code": "威嚇咆哮発出",
        "category": "言説",
        "property": "音響威嚇",
        "dimension": "恐怖的-警告的"
      },
      {
        "code": "河川絶対支配",
        "category": "存在論",
        "property": "領域統制",
        "dimension": "完全支配-影響圏維持"
      },
      {
        "code": "自然威力示現",
        "category": "存在論",
        "property": "力の顕示",
        "dimension": "圧倒的-印象的"
      }
    ]
  },
  {
    "id": "hashira_no_sei",
    "open_codes": [
      {
        "code": "地震吸収防護",
        "category": "行動様式",
        "property": "災害対応",
        "dimension": "完全防護-軽減"
      },
      {
        "code": "危険感知警告",
        "category": "行動様式",
        "property": "予警機能",
        "dimension": "即座-遅延"
      },
      {
        "code": "構造自己修復",
        "category": "行動様式",
        "property": "再生能力",
        "dimension": "完全修復-部分補強"
      },
      {
        "code": "安定保証宣言",
        "category": "言説",
        "property": "信頼供与",
        "dimension": "絶対的-条件付き"
      },
      {
        "code": "家族永続守護",
        "category": "存在論",
        "property": "継続保護",
        "dimension": "世代間継続-限定期間"
      },
      {
        "code": "人工自然調和",
        "category": "存在論",
        "property": "環境統合",
        "dimension": "完全調和-適度統合"
      }
    ]
  },
  {
    "id": "pincoya",
    "open_codes": [
      {
        "code": "方向別踊り分化",
        "category": "行動様式",
        "property": "儀礼的動作",
        "dimension": "厳格-柔軟"
      },
      {
        "code": "海洋生物魅了",
        "category": "行動様式",
        "property": "生物統制",
        "dimension": "完全支配-影響のみ"
      },
      {
        "code": "天候海況操作",
        "category": "行動様式",
        "property": "環境統制",
        "dimension": "直接操作-間接影響"
      },
      {
        "code": "無言身体表現",
        "category": "言説",
        "property": "非言語伝達",
        "dimension": "明確-曖昧"
      },
      {
        "code": "漁業生態調和",
        "category": "存在論",
        "property": "資源管理",
        "dimension": "厳格管理-柔軟調整"
      },
      {
        "code": "海陸境界媒介",
        "category": "存在論",
        "property": "領域仲介",
        "dimension": "完全統合-分離維持"
      }
    ]
  },
  {
    "id": "matsu_no_sei",
    "open_codes": [
      {
        "code": "数百年持続存在",
        "category": "行動様式",
        "property": "時間的持続",
        "dimension": "永続的-長期的"
      },
      {
        "code": "夫婦和合加護",
        "category": "行動様式",
        "property": "関係性支援",
        "dimension": "積極的-消極的"
      },
      {
        "code": "人樹形態変化",
        "category": "行動様式",
        "property": "姿態変換",
        "dimension": "完全変身-部分変化"
      },
      {
        "code": "深愛長寿語り",
        "category": "言説",
        "property": "人生哲学",
        "dimension": "確信的-示唆的"
      },
      {
        "code": "縁結び良縁供与",
        "category": "存在論",
        "property": "運命調整",
        "dimension": "積極的仲介-環境整備"
      },
      {
        "code": "時間持続性媒介",
        "category": "存在論",
        "property": "時間的架橋",
        "dimension": "完全統合-部分接続"
      }
    ]
  },
  {
    "id": "matsu_rei",
    "open_codes": [
      {
        "code": "老翁姿顕現",
        "category": "行動様式",
        "property": "形態表出",
        "dimension": "明確-曖昧"
      },
      {
        "code": "正月巡回守護",
        "category": "行動様式",
        "property": "季節的活動",
        "dimension": "定期的-不定期"
      },
      {
        "code": "嵐夜枝揺らし",
        "category": "行動様式",
        "property": "保護行動",
        "dimension": "積極的-受動的"
      },
      {
        "code": "伝統価値詠唱",
        "category": "言説",
        "property": "教訓伝達",
        "dimension": "格調高い-平易"
      },
      {
        "code": "家系継続保護",
        "category": "存在論",
        "property": "世代間維持",
        "dimension": "永続的-限定的"
      },
      {
        "code": "千年時間軸保証",
        "category": "存在論",
        "property": "時間的保障",
        "dimension": "絶対的-相対的"
      },
      {
        "code": "聖時秩序維持",
        "category": "存在論",
        "property": "時間統制",
        "dimension": "厳格-寛容"
      }
    ]
  },
  {
    "id": "kurohige_kaizoku_rei",
    "open_codes": [
      {
        "code": "道徳的審査",
        "category": "行動様式",
        "property": "心の正邪を見極める",
        "dimension": "厳格-寛容"
      },
      {
        "code": "応報的制裁",
        "category": "関係性",
        "property": "欲深い者への処罰",
        "dimension": "即座-遅延"
      },
      {
        "code": "隠された富の媒介",
        "category": "存在論",
        "property": "財宝の在り処を示す",
        "dimension": "秘匿-開示"
      },
      {
        "code": "海洋権威の行使",
        "category": "言説",
        "property": "海の支配者としての威厳",
        "dimension": "威圧-親和"
      },
      {
        "code": "正義執行者の役割",
        "category": "変容",
        "property": "道徳的秩序の維持",
        "dimension": "保守-革新"
      }
    ]
  },
  {
    "id": "pishacha",
    "open_codes": [
      {
        "code": "腐敗への親和",
        "category": "行動様式",
        "property": "死体や汚物への執着",
        "dimension": "強烈-微弱"
      },
      {
        "code": "精神的寄生",
        "category": "関係性",
        "property": "弱者への憑依",
        "dimension": "支配-従属"
      },
      {
        "code": "不浄の拡散",
        "category": "存在論",
        "property": "汚れの象徴的機能",
        "dimension": "集中-分散"
      },
      {
        "code": "退行的言語",
        "category": "言説",
        "property": "原始的な欲求表現",
        "dimension": "複雑-単純"
      },
      {
        "code": "浄化による排除",
        "category": "変容",
        "property": "儀礼的除去可能性",
        "dimension": "永続-一時"
      }
    ]
  },
  {
    "id": "pishacha_spirit",
    "open_codes": [
      {
        "code": "生命力の簒奪",
        "category": "行動様式",
        "property": "病気の悪化促進",
        "dimension": "活発-消極"
      },
      {
        "code": "死の加速化",
        "category": "存在論",
        "property": "自然過程の操作",
        "dimension": "自然-人工"
      },
      {
        "code": "汚染の循環",
        "category": "関係性",
        "property": "不浄の連鎖反応",
        "dimension": "拡大-収縮"
      },
      {
        "code": "食欲的言説",
        "category": "言説",
        "property": "肉体的欲求の直接表現",
        "dimension": "露骨-暗示"
      },
      {
        "code": "宗教的統制",
        "category": "変容",
        "property": "ブラーミン権威への従属",
        "dimension": "抵抗-服従"
      }
    ]
  },
  {
    "id": "pishtaco",
    "open_codes": [
      {
        "code": "植民地的模擬",
        "category": "行動様式",
        "property": "外国人への変装",
        "dimension": "真正-偽装"
      },
      {
        "code": "医療的搾取",
        "category": "関係性",
        "property": "治療を装った加害",
        "dimension": "治癒-破壊"
      },
      {
        "code": "文化的境界侵犯",
        "category": "存在論",
        "property": "先住民と移民の対立",
        "dimension": "内部-外部"
      },
      {
        "code": "偽善的誘惑",
        "category": "言説",
        "property": "善意を装った悪意",
        "dimension": "誠実-欺瞞"
      },
      {
        "code": "搾取構造の永続",
        "category": "変容",
        "property": "植民地関係の再生産",
        "dimension": "解放-支配"
      }
    ]
  },
  {
    "id": "pixiu",
    "open_codes": [
      {
        "code": "財宝蓄積",
        "category": "行動様式",
        "property": "富の集約と保持",
        "dimension": "蓄積-放出"
      },
      {
        "code": "商業的守護",
        "category": "関係性",
        "property": "経済活動への加護",
        "dimension": "支援-妨害"
      },
      {
        "code": "霊的財運",
        "category": "存在論",
        "property": "物質と霊性の調和",
        "dimension": "統合-分離"
      },
      {
        "code": "富の宣言",
        "category": "言説",
        "property": "財運への確信",
        "dimension": "断定-疑問"
      },
      {
        "code": "邪気排除",
        "category": "変容",
        "property": "負の要素の除去",
        "dimension": "浄化-汚染"
      }
    ]
  },
  {
    "id": "subaru_spirit",
    "open_codes": [
      {
        "code": "集合的行動",
        "category": "行動様式",
        "property": "複数星霊の協力",
        "dimension": "集団-個体"
      },
      {
        "code": "農事指導",
        "category": "関係性",
        "property": "農民への時期告知",
        "dimension": "指導-従属"
      },
      {
        "code": "天地媒介",
        "category": "存在論",
        "property": "宇宙と地上の橋渡し",
        "dimension": "天界-地上"
      },
      {
        "code": "協調の言説",
        "category": "言説",
        "property": "団結の重要性",
        "dimension": "統一-分散"
      },
      {
        "code": "季節的変容",
        "category": "変容",
        "property": "農事暦に応じた変化",
        "dimension": "周期-直線"
      }
    ]
  },
  {
    "id": "ume_rei",
    "open_codes": [
      {
        "code": "超空間移動",
        "category": "行動様式",
        "property": "瞬間的地理移動",
        "dimension": "迅速-緩慢"
      },
      {
        "code": "感情的共鳴",
        "category": "関係性",
        "property": "主人の心情への応答",
        "dimension": "共感-無関心"
      },
      {
        "code": "忠愛の具現",
        "category": "存在論",
        "property": "無条件の献身",
        "dimension": "絶対-条件"
      },
      {
        "code": "忠義の言説",
        "category": "言説",
        "property": "主従関係への言及",
        "dimension": "献身-反抗"
      },
      {
        "code": "学問的変容",
        "category": "変容",
        "property": "知的成長への影響",
        "dimension": "向上-停滞"
      }
    ]
  },
  {
    "id": "poludnitsa",
    "open_codes": [
      {
        "code": "時刻的規律",
        "category": "行動様式",
        "property": "正午の労働禁止",
        "dimension": "厳格-柔軟"
      },
      {
        "code": "知的試練",
        "category": "関係性",
        "property": "謎かけによる試験",
        "dimension": "挑戦-支援"
      },
      {
        "code": "自然リズム執行",
        "category": "存在論",
        "property": "生体時計の強制",
        "dimension": "自然-人工"
      },
      {
        "code": "警告的言説",
        "category": "言説",
        "property": "労働リスクへの問いかけ",
        "dimension": "警告-推奨"
      },
      {
        "code": "致命的制裁",
        "category": "変容",
        "property": "生死による矯正",
        "dimension": "極端-穏健"
      }
    ]
  },
  {
    "id": "ikenushi",
    "open_codes": [
      {
        "code": "瞑想的静寂",
        "category": "行動様式",
        "property": "長時間の沈黙",
        "dimension": "静的-動的"
      },
      {
        "code": "生態系管理",
        "category": "関係性",
        "property": "環境の調整",
        "dimension": "管理-放任"
      },
      {
        "code": "水鏡機能",
        "category": "存在論",
        "property": "内面反映の媒体",
        "dimension": "透明-不透明"
      },
      {
        "code": "美的言説",
        "category": "言説",
        "property": "静寂と美への言及",
        "dimension": "美的-実用"
      },
      {
        "code": "保護的変容",
        "category": "変容",
        "property": "環境防御への転換",
        "dimension": "守備-攻撃"
      }
    ]
  },
  {
    "id": "ike_nushi",
    "open_codes": [
      {
        "code": "水資源管理",
        "category": "行動様式",
        "property": "水位と雨の調整",
        "dimension": "制御-自然"
      },
      {
        "code": "農業支援",
        "category": "関係性",
        "property": "農民への水供給",
        "dimension": "協力-対立"
      },
      {
        "code": "神聖性維持",
        "category": "存在論",
        "property": "水の霊的価値保護",
        "dimension": "神聖-世俗"
      },
      {
        "code": "ゆるやかな言説",
        "category": "言説",
        "property": "穏和な表現",
        "dimension": "穏和-激烈"
      },
      {
        "code": "浄化的変容",
        "category": "変容",
        "property": "汚染への対応",
        "dimension": "清浄-汚濁"
      }
    ]
  },
  {
    "id": "pontianak",
    "open_codes": [
      {
        "code": "誘惑的擬態",
        "category": "行動様式",
        "property": "美女への変身",
        "dimension": "魅惑-嫌悪"
      },
      {
        "code": "産育的執着",
        "category": "関係性",
        "property": "出産と育児への関心",
        "dimension": "愛情-憎悪"
      },
      {
        "code": "欠損の隠蔽",
        "category": "存在論",
        "property": "背中の穴への羞恥",
        "dimension": "完全-不完全"
      },
      {
        "code": "母性的言説",
        "category": "言説",
        "property": "子どもへの言及",
        "dimension": "慈愛-復讐"
      },
      {
        "code": "復讐的変容",
        "category": "変容",
        "property": "死から復活への転換",
        "dimension": "受動-能動"
      }
    ]
  },
  {
    "id": "nat_popa",
    "open_codes": [
      {
        "code": "花の祝福",
        "category": "行動様式",
        "property": "植物的恩恵の授与",
        "dimension": "豊穣-枯渇"
      },
      {
        "code": "母性的保護",
        "category": "関係性",
        "property": "女性と子どもの守護",
        "dimension": "保護-放置"
      },
      {
        "code": "山岳霊性",
        "category": "存在論",
        "property": "聖山との一体化",
        "dimension": "地上-天上"
      },
      {
        "code": "教育的言説",
        "category": "言説",
        "property": "自然の知恵の伝授",
        "dimension": "教導-沈黙"
      },
      {
        "code": "季節的変容",
        "category": "変容",
        "property": "農事サイクルへの適応",
        "dimension": "変化-不変"
      }
    ]
  },
  {
    "id": "popobawa",
    "open_codes": [
      {
        "code": "夜間侵入",
        "category": "行動様式",
        "property": "家屋への不法侵入",
        "dimension": "侵入-退散"
      },
      {
        "code": "集団恐怖誘発",
        "category": "関係性",
        "property": "共同体全体への影響",
        "dimension": "集団-個人"
      },
      {
        "code": "周期的出現",
        "category": "存在論",
        "property": "一定間隔での活動",
        "dimension": "周期-不規則"
      },
      {
        "code": "脅迫的言説",
        "category": "言説",
        "property": "秘密の暴露による威嚇",
        "dimension": "威嚇-安慰"
      },
      {
        "code": "恐怖による結束",
        "category": "変容",
        "property": "不安から団結への転換",
        "dimension": "分裂-統合"
      }
    ]
  },
  {
    "id": "preta_hungry_ghost",
    "open_codes": [
      {
        "code": "永続的飢餓",
        "category": "行動様式",
        "property": "満たされぬ食欲",
        "dimension": "渇望-充足"
      },
      {
        "code": "業報的苦悩",
        "category": "関係性",
        "property": "因果応報の体現",
        "dimension": "苦痛-快楽"
      },
      {
        "code": "欲望の物質化",
        "category": "存在論",
        "property": "生前の強欲の顕現",
        "dimension": "精神-物質"
      },
      {
        "code": "絶望的言説",
        "category": "言説",
        "property": "苦痛の直接表現",
        "dimension": "絶望-希望"
      },
      {
        "code": "供養による解放",
        "category": "変容",
        "property": "宗教的救済への依存",
        "dimension": "束縛-解脱"
      }
    ]
  },
  {
    "id": "universal_chaos_primordial",
    "open_codes": [
      {
        "code": "無形の流動",
        "category": "行動様式",
        "property": "形態の不固定性",
        "dimension": "流動-固定"
      },
      {
        "code": "秩序の溶解",
        "category": "関係性",
        "property": "既存法則の無効化",
        "dimension": "混沌-秩序"
      },
      {
        "code": "根源的前在",
        "category": "存在論",
        "property": "全存在の前提条件",
        "dimension": "根源-派生"
      },
      {
        "code": "無言の存在",
        "category": "言説",
        "property": "言語を超越した状態",
        "dimension": "無言-発話"
      },
      {
        "code": "創造破壊統一",
        "category": "変容",
        "property": "対立概念の同時実現",
        "dimension": "統一-分裂"
      }
    ]
  },
  {
    "id": "tieshan_gongzhu",
    "open_codes": [
      {
        "code": "自然力操作による境界制御",
        "category": "行動様式",
        "property": "環境操作能力",
        "dimension": "強力-選択的"
      },
      {
        "code": "母性的保護意識",
        "category": "関係性",
        "property": "家族防衛",
        "dimension": "献身的-排他的"
      },
      {
        "code": "威嚇による領域防衛",
        "category": "行動様式",
        "property": "侵入者対応",
        "dimension": "激烈-即座"
      },
      {
        "code": "条件付き恩恵供与",
        "category": "関係性",
        "property": "人間との交渉",
        "dimension": "実利的-取引的"
      },
      {
        "code": "女性的自然支配の体現",
        "category": "存在論的",
        "property": "宇宙論的位置",
        "dimension": "超越的-象徴的"
      }
    ]
  },
  {
    "id": "pukwudgie",
    "open_codes": [
      {
        "code": "偽善的誘導戦術",
        "category": "行動様式",
        "property": "欺瞞手法",
        "dimension": "巧妙-悪意的"
      },
      {
        "code": "復讐的制裁行動",
        "category": "関係性",
        "property": "人間への報復",
        "dimension": "計画的-持続的"
      },
      {
        "code": "親切の仮面による信頼獲得",
        "category": "言説",
        "property": "偽装話法",
        "dimension": "表面的-操作的"
      },
      {
        "code": "生態的秩序の武力執行",
        "category": "存在論的",
        "property": "自然正義",
        "dimension": "超自然的-制裁的"
      },
      {
        "code": "友情裏切りへの報復衝動",
        "category": "動機",
        "property": "感情的動機",
        "dimension": "怨念的-執念的"
      }
    ]
  },
  {
    "id": "qalupalik",
    "open_codes": [
      {
        "code": "魅惑的誘引による危険回避教育",
        "category": "行動様式",
        "property": "教育手法",
        "dimension": "誘惑的-教訓的"
      },
      {
        "code": "極地生存規律の強制",
        "category": "関係性",
        "property": "規範執行",
        "dimension": "厳格-保護的"
      },
      {
        "code": "母性的包摂と変容",
        "category": "行動様式",
        "property": "変身付与",
        "dimension": "包括的-変容的"
      },
      {
        "code": "従順性による選別機能",
        "category": "関係性",
        "property": "道徳判断",
        "dimension": "差別的-教育的"
      },
      {
        "code": "海陸境界での生存知識伝承",
        "category": "存在論的",
        "property": "知識媒介",
        "dimension": "世代間-継承的"
      }
    ]
  },
  {
    "id": "qareen",
    "open_codes": [
      {
        "code": "不可分離的影響力行使",
        "category": "関係性",
        "property": "宿主依存",
        "dimension": "永続的-密着的"
      },
      {
        "code": "道徳的弱点の探知と拡大",
        "category": "行動様式",
        "property": "誘惑戦術",
        "dimension": "心理的-持続的"
      },
      {
        "code": "内なる悪への囁きかけ",
        "category": "言説",
        "property": "内的対話",
        "dimension": "潜在的-継続的"
      },
      {
        "code": "道徳的試練の提供",
        "category": "存在論的",
        "property": "精神的試練",
        "dimension": "恒常的-二元的"
      },
      {
        "code": "人格内部の悪の具現化",
        "category": "存在論的",
        "property": "内的悪性",
        "dimension": "心理的-象徴的"
      }
    ]
  },
  {
    "id": "qarina",
    "open_codes": [
      {
        "code": "夢現境界での侵入攻撃",
        "category": "行動様式",
        "property": "意識侵入",
        "dimension": "潜在的-攻撃的"
      },
      {
        "code": "外見模倣による同一化",
        "category": "変容",
        "property": "視覚的複製",
        "dimension": "完全的-欺瞞的"
      },
      {
        "code": "嫉妬による関係破壊",
        "category": "関係性",
        "property": "愛情独占",
        "dimension": "破壊的-排他的"
      },
      {
        "code": "愛着の病的歪曲",
        "category": "動機",
        "property": "愛情表現",
        "dimension": "強迫的-支配的"
      },
      {
        "code": "潜在意識への直接介入",
        "category": "言説",
        "property": "無意識操作",
        "dimension": "深層的-操作的"
      }
    ]
  },
  {
    "id": "qilin",
    "open_codes": [
      {
        "code": "完全非暴力の実践",
        "category": "行動様式",
        "property": "倫理的行動",
        "dimension": "絶対的-一貫的"
      },
      {
        "code": "聖性出現の予告機能",
        "category": "存在論的",
        "property": "吉兆媒介",
        "dimension": "予言的-象徴的"
      },
      {
        "code": "仁徳に関する穏和な教示",
        "category": "言説",
        "property": "道徳教授",
        "dimension": "温和-権威的"
      },
      {
        "code": "道徳的模範の体現",
        "category": "存在論的",
        "property": "理想的存在",
        "dimension": "超越的-完全的"
      },
      {
        "code": "暴力的状況での沈黙回避",
        "category": "行動様式",
        "property": "不参加原則",
        "dimension": "一貫的-消極的"
      }
    ]
  },
  {
    "id": "qiongqi",
    "open_codes": [
      {
        "code": "善悪価値の完全逆転",
        "category": "行動様式",
        "property": "道徳倒錯",
        "dimension": "絶対的-意図的"
      },
      {
        "code": "善人への選択的捕食",
        "category": "関係性",
        "property": "道徳的選別",
        "dimension": "逆説的-破壊的"
      },
      {
        "code": "悪人への象徴的援助",
        "category": "関係性",
        "property": "反道徳支援",
        "dimension": "皮肉的-逆説的"
      },
      {
        "code": "正義への嘲笑的挑発",
        "category": "言説",
        "property": "反倫理話法",
        "dimension": "嘲弄的-挑戦的"
      },
      {
        "code": "道徳秩序の混沌化",
        "category": "存在論的",
        "property": "価値転覆",
        "dimension": "根本的-破壊的"
      }
    ]
  },
  {
    "id": "xiwangmu",
    "open_codes": [
      {
        "code": "不老不死の選択的授与",
        "category": "行動様式",
        "property": "永生管理",
        "dimension": "選択的-権威的"
      },
      {
        "code": "天地秩序の監督権行使",
        "category": "存在論的",
        "property": "宇宙統治",
        "dimension": "絶対的-包括的"
      },
      {
        "code": "威厳ある女神的振舞い",
        "category": "行動様式",
        "property": "神格表現",
        "dimension": "荘厳-超越的"
      },
      {
        "code": "宇宙法則の格調高い教示",
        "category": "言説",
        "property": "神的教授",
        "dimension": "権威的-神秘的"
      },
      {
        "code": "生死境界の超越管理",
        "category": "存在論的",
        "property": "存在論的支配",
        "dimension": "超越的-永続的"
      }
    ]
  },
  {
    "id": "quetzalcoatl",
    "open_codes": [
      {
        "code": "文明技術の人類伝授",
        "category": "行動様式",
        "property": "知識供与",
        "dimension": "建設的-進歩的"
      },
      {
        "code": "自然現象の調和的制御",
        "category": "行動様式",
        "property": "気象操作",
        "dimension": "調和的-恩恵的"
      },
      {
        "code": "神人変身による存在変容",
        "category": "変容",
        "property": "形態転換",
        "dimension": "流動的-象徴的"
      },
      {
        "code": "詩的宇宙論の教示",
        "category": "言説",
        "property": "哲学的教授",
        "dimension": "美的-深遠的"
      },
      {
        "code": "文明進化の触媒機能",
        "category": "存在論的",
        "property": "進歩促進",
        "dimension": "発展的-創造的"
      },
      {
        "code": "周期的帰還の予告",
        "category": "存在論的",
        "property": "時間的循環",
        "dimension": "予言的-周期的"
      }
    ]
  },
  {
    "id": "rabbit_trickster",
    "open_codes": [
      {
        "code": "知恵による力関係の逆転",
        "category": "行動様式",
        "property": "智謀戦術",
        "dimension": "機敏-逆転的"
      },
      {
        "code": "瞬時退避による危険回避",
        "category": "行動様式",
        "property": "生存技術",
        "dimension": "迅速-巧妙"
      },
      {
        "code": "変身による社会潜入",
        "category": "変容",
        "property": "身分偽装",
        "dimension": "流動-適応的"
      },
      {
        "code": "機転による嘘の連発",
        "category": "言説",
        "property": "即興欺瞞",
        "dimension": "創造的-操作的"
      },
      {
        "code": "弱者への生存知恵の伝授",
        "category": "関係性",
        "property": "知識供与",
        "dimension": "共感的-教育的"
      },
      {
        "code": "権力構造への風刺的批判",
        "category": "存在論的",
        "property": "社会批評",
        "dimension": "風刺的-転覆的"
      }
    ]
  },
  {
    "id": "rabisu_mesopotamia",
    "open_codes": [
      {
        "code": "境界空間での潜伏待機",
        "category": "行動様式",
        "property": "領域占拠",
        "dimension": "持続的-隠蔽的"
      },
      {
        "code": "突発的恐怖の植え付け",
        "category": "行動様式",
        "property": "驚愕攻撃",
        "dimension": "瞬間的-強烈"
      },
      {
        "code": "油断の瞬間を狙った行動",
        "category": "行動様式",
        "property": "機会捕捉",
        "dimension": "計算的-待機的"
      },
      {
        "code": "暗闇からの不気味な囁き",
        "category": "言説",
        "property": "恐怖音声",
        "dimension": "神秘的-威嚇的"
      },
      {
        "code": "敷居における支配権の主張",
        "category": "存在論的",
        "property": "境界支配",
        "dimension": "占有的-威圧的"
      }
    ]
  }
]